{
	"configurations" : 
	[
		{
			"directories" : 
			[
				{
					"build" : ".",
					"jsonFile" : "directory-.-Debug-f5ebdc15457944623624.json",
					"minimumCMakeVersion" : 
					{
						"string" : "3.24"
					},
					"projectIndex" : 0,
					"source" : ".",
					"targetIndexes" : 
					[
						0
					]
				}
			],
			"name" : "Debug",
			"projects" : 
			[
				{
					"directoryIndexes" : 
					[
						0
					],
					"name" : "6",
					"targetIndexes" : 
					[
						0
					]
				}
			],
			"targets" : 
			[
				{
					"directoryIndex" : 0,
					"id" : "6::@6890427a1f51a3e7e1df",
					"jsonFile" : "target-6-Debug-b0920810a4fc172a4c78.json",
					"name" : "6",
					"projectIndex" : 0
				}
			]
		}
	],
	"kind" : "codemodel",
	"paths" : 
	{
		"build" : "/Users/tgspock/Documents/C primer/6/cmake-build-debug",
		"source" : "/Users/tgspock/Documents/C primer/6"
	},
	"version" : 
	{
		"major" : 2,
		"minor" : 4
	}
}
